coloromma/__init__.py
coloromma/ansi.py
coloromma/ansitowin32.py
coloromma/initialise.py
coloromma/win32.py
coloromma/winterm.py
coloromma/tests/__init__.py
coloromma/tests/ansi_test.py
coloromma/tests/ansitowin32_test.py
coloromma/tests/initialise_test.py
coloromma/tests/isatty_test.py
coloromma/tests/utils.py
coloromma/tests/winterm_test.py
coloromma-2.2.7.dist-info/LICENSE.txt
coloromma-2.2.7.dist-info/METADATA
coloromma-2.2.7.dist-info/WHEEL
coloromma-2.2.7.dist-info/top_level.txt
coloromma-2.2.7.dist-info/RECORD
