Metadata-Version: 2.1
Name: coloromma
Version: 2.2.7
Summary: python package to handle colorful outputs
Home-page: https://github.com/coloramma
Author: Turtley
Author-email: turtley120@gmail.com
Classifier: Programming Language :: Python :: 3
Classifier: License :: OSI Approved :: MIT License
Classifier: Operating System :: OS Independent
Requires-Python: >=3.7
License-File: LICENSE.txt
